clioecsv/__init__.py
clioecsv/clioecsv.py
clioecsv/sort_ratecard.py
clioecsv-1.4.dist-info/LICENSE
clioecsv-1.4.dist-info/METADATA
clioecsv-1.4.dist-info/WHEEL
clioecsv-1.4.dist-info/top_level.txt
clioecsv-1.4.dist-info/RECORD
