Metadata-Version: 2.1
Name: clioecsv
Version: 1.4
Summary: A module to import, transform (remove top / bottom, distinct, append and merge) and export to csv
Author: Cheny Lioe
Author-email: chenylioe@yahoo.com
License: UNKNOWN
Keywords: csv file,txt file
Platform: UNKNOWN
License-File: LICENSE
